odoo8_addon_medical_pharmacy_us-8.0.1.1.0.99.dev4-py2.7-nspkg.pth
odoo8_addon_medical_pharmacy_us-8.0.1.1.0.99.dev4.dist-info/DESCRIPTION.rst
odoo8_addon_medical_pharmacy_us-8.0.1.1.0.99.dev4.dist-info/METADATA
odoo8_addon_medical_pharmacy_us-8.0.1.1.0.99.dev4.dist-info/RECORD
odoo8_addon_medical_pharmacy_us-8.0.1.1.0.99.dev4.dist-info/WHEEL
odoo8_addon_medical_pharmacy_us-8.0.1.1.0.99.dev4.dist-info/metadata.json
odoo8_addon_medical_pharmacy_us-8.0.1.1.0.99.dev4.dist-info/namespace_packages.txt
odoo8_addon_medical_pharmacy_us-8.0.1.1.0.99.dev4.dist-info/top_level.txt
odoo_addons/medical_pharmacy_us/README.rst
odoo_addons/medical_pharmacy_us/__init__.py
odoo_addons/medical_pharmacy_us/__openerp__.py
odoo_addons/medical_pharmacy_us/i18n/pt_BR.po
odoo_addons/medical_pharmacy_us/models/__init__.py
odoo_addons/medical_pharmacy_us/models/medical_pharmacy.py
